aiplatform/__init__.py
aiplatform/_base_client.py
aiplatform/_client.py
aiplatform/_compat.py
aiplatform/_constants.py
aiplatform/_exceptions.py
aiplatform/_files.py
aiplatform/_models.py
aiplatform/_qs.py
aiplatform/_resource.py
aiplatform/_response.py
aiplatform/_streaming.py
aiplatform/_types.py
aiplatform/version.py
aiplatform/_utils/__init__.py
aiplatform/_utils/_logs.py
aiplatform/_utils/_proxy.py
aiplatform/_utils/_streams.py
aiplatform/_utils/_sync.py
aiplatform/_utils/_transform.py
aiplatform/_utils/_typing.py
aiplatform/_utils/_utils.py
aiplatform/lib/.keep
aiplatform/resources/__init__.py
aiplatform/resources/chat_completions.py
aiplatform/resources/completions.py
aiplatform/resources/embeddings.py
aiplatform/resources/models.py
aiplatform/resources/moderations.py
aiplatform/resources/images/__init__.py
aiplatform/resources/images/generations.py
aiplatform/resources/images/images.py
aiplatform/types/__init__.py
aiplatform/types/chat_completion_create_chunk_response.py
aiplatform/types/chat_completion_create_params.py
aiplatform/types/chat_completion_create_response.py
aiplatform/types/completion_create_params.py
aiplatform/types/completion_create_response.py
aiplatform/types/embedding_create_params.py
aiplatform/types/embedding_create_response.py
aiplatform/types/model_list_response.py
aiplatform/types/moderation_create_params.py
aiplatform/types/moderation_create_response.py
aiplatform/types/images/__init__.py
aiplatform/types/images/generation_create_params.py
aiplatform/types/images/generation_create_response.py
kilm_aiplatform-0.3.0.dist-info/METADATA
kilm_aiplatform-0.3.0.dist-info/WHEEL
kilm_aiplatform-0.3.0.dist-info/licenses/LICENSE
kilm_aiplatform-0.3.0.dist-info/RECORD
