Metadata-Version: 2.3
Name: kilm-aiplatform
Version: 0.3.0
Summary: The official Python library for the AI Platform API
Project-URL: Homepage, https://zalogit2.zing.vn/nlp/kilm/ai-platform
Project-URL: Documentation, https://zalogit2.zing.vn/nlp/kilm/ai-platform
Project-URL: Repository, https://zalogit2.zing.vn/nlp/kilm/ai-platform
Author-email: vietnh8 <vietnh8@vng.com.vn>
License-Expression: MIT
License-File: LICENSE
Classifier: Development Status :: 4 - Beta
Classifier: Programming Language :: Python
Classifier: Programming Language :: Python :: 3.8
Classifier: Programming Language :: Python :: 3.9
Classifier: Programming Language :: Python :: 3.10
Classifier: Programming Language :: Python :: 3.11
Classifier: Programming Language :: Python :: 3.12
Classifier: Programming Language :: Python :: Implementation :: CPython
Classifier: Programming Language :: Python :: Implementation :: PyPy
Requires-Python: >=3.8
Requires-Dist: distro<2,>=1.9.0
Requires-Dist: httpx>=0.27.0
Requires-Dist: pydantic<3.0.0,>=2.7.1
Requires-Dist: sniffio
